setup.cfg
setup.py
tinycm/__init__.py
tinycm/__main__.py
tinycm/backup.py
tinycm/basedefinition.py
tinycm/graph.py
tinycm/log.py
tinycm/parser.py
tinycm/plugin.py
tinycm/state.py
tinycm/utils.py
tinycm.egg-info/PKG-INFO
tinycm.egg-info/SOURCES.txt
tinycm.egg-info/dependency_links.txt
tinycm.egg-info/entry_points.txt
tinycm.egg-info/requires.txt
tinycm.egg-info/top_level.txt
tinycm/definitions/__init__.py
tinycm/definitions/file.py
tinycm/definitions/git.py
tinycm/definitions/link.py
tinycm/definitions/package.py
tinycm/definitions/user.py